COPYING
CREDITS
ChangeLog
MANIFEST.in
Makefile
README.html
README.txt
ToDo
setup.py
watchvideo.desktop
WatchVideo.egg-info/PKG-INFO
WatchVideo.egg-info/SOURCES.txt
WatchVideo.egg-info/dependency_links.txt
WatchVideo.egg-info/entry_points.txt
WatchVideo.egg-info/requires.txt
WatchVideo.egg-info/top_level.txt
WatchVideo.egg-info/zip-safe
media/README
media/Web-browser.png
media/Web-browser.svg
media/ask-quality.png
media/custom-quality.png
media/dialog-ok-apply.png
media/edit-clear-list.png
media/edit-copy.png
media/error.png
media/folder-open.png
media/harddisk-add.png
media/high-quality.png
media/internet-download.png
media/internet-play.png
media/klipper.png
media/list-add.svg
media/list-remove.png
media/low-quality.png
media/pause.png
media/playlist_refresh.png
media/preferences.png
media/preferences.svg
media/quit.png
media/quit.svg
media/refresh.png
media/search.png
media/start.png
media/stop.png
media/trash.png
media/watchvideo-200x200.png
media/watchvideo-32x32.png
media/watchvideo-48x48.png
media/watchvideo.svg
po/cs.qm
po/cs.ts
po/es.qm
po/es.ts
po/pl.qm
po/pl.ts
po/pt.qm
po/pt.ts
src_ui/icons.qrc
src_ui/translations.qrc
src_ui/ui_about.ui
src_ui/ui_add_videos.ui
src_ui/ui_main.ui
src_ui/ui_preferences.ui
tests_watchvideo/__init__.py
tests_watchvideo/imports.py
tests_watchvideo/main.py
utils/check-dependencies.sh
utils/install-desktop-entry.sh
watchvideo/__init__.py
watchvideo/about.py
watchvideo/add_videos.py
watchvideo/constants.py
watchvideo/gui_utils.py
watchvideo/icons_rc.py
watchvideo/main.py
watchvideo/notification.py
watchvideo/player.py
watchvideo/preferences.py
watchvideo/qt.py
watchvideo/search_widget.py
watchvideo/searchfield.py
watchvideo/searchparams.py
watchvideo/settings.py
watchvideo/slider.py
watchvideo/threads.py
watchvideo/translations_rc.py
watchvideo/tree_widget_item.py
watchvideo/ui_about.py
watchvideo/ui_add_videos.py
watchvideo/ui_choose_format.py
watchvideo/ui_main.py
watchvideo/ui_preferences.py
watchvideo/utils.py
watchvideo/video_info.py
watchvideo/vlc.py
watchvideo/watchvideo_cli.py
watchvideo/watchvideo_gui.py
watchvideo/youtubesearch.py