Metadata-Version: 1.0
Name: WatchVideo
Version: 2.2.1
Summary: A small application to play or download videos from various YouTube-like sites.
Home-page: http://qt-apps.org/content/show.php/WatchVideo?content=128368
Author: Carlos Pais
Author-email: freemind@lavabit.com
License: GNU Affero General Public License v3 or later
Download-URL: http://download.savannah.gnu.org/releases/watchvideo/
Platform: UNKNOWN
Classifier: Development Status :: 4 - Beta
Classifier: Environment :: Console
Classifier: Environment :: X11 Applications :: Qt
Classifier: Intended Audience :: End Users/Desktop
Classifier: License :: OSI Approved :: GNU Affero General Public License v3
